xbus/__init__.py
xbus/client.py
xbus/error.py
xbus/ldict.py
xbus-0.1.6.dist-info/METADATA
xbus-0.1.6.dist-info/RECORD
xbus-0.1.6.dist-info/WHEEL
xbus-0.1.6.dist-info/top_level.txt
